{
  "_component": "footer",
  "_version": "6.3",
  "_engine": "footerQuadTree.js",
  "_stack": "RODUX: StateJS → RatioEngine → cssJSON → QuadTree → CSS vars",
  "_comment": "Profiles are mathematical constraint sets. Device-aware: touch vs pointer. Desktop resized small ≠ phone.",

  "profiles": [
    {
      "name": "compact-portrait",
      "_comment": "Touch device, portrait, ≤767px. Wireframe layout: title row → transport row → seek+time row → nav row → logo row. Everything stacks full-width.",
      "device": "touch",
      "orientation": "portrait",
      "maxWidth": 767,
      "stacked": true,
      "height": "auto",
      "volumeVisible": false,
      "order": { "player": 1, "nav": 2, "logo": 3 },
      "zones": {
        "player": { "minPx": 0 },
        "nav":    { "minPx": 0 },
        "logo":   { "minPx": 0 }
      },
      "vars": {
        "--player-btn-size": "36px",
        "--player-icon-size": "24px",
        "--player-btn-gap": "6px",
        "--player-title-max-w": "100%",
        "--player-title-font": "14px",
        "--player-time-font": "12px",
        "--seek-max-w": "none",
        "--seek-min-w": "40%",
        "--seek-height": "8px",
        "--nav-font": "13px",
        "--nav-padding": "10px 14px",
        "--logo-img-h": "16px",
        "--logo-tag-font": "9px",
        "--logo-padding": "6px 10px",
        "--user-icon-size": "16px",
        "--user-name-font": "10px",
        "--user-cell-padding": "6px 10px",
        "--toggle-font": "11px",
        "--toggle-padding": "6px 16px"
      }
    },
    {
      "name": "compact-landscape",
      "_comment": "Touch device, landscape, ≤767px height effective. Tighter stacked layout.",
      "device": "touch",
      "orientation": "landscape",
      "maxWidth": 767,
      "stacked": true,
      "height": "auto",
      "volumeVisible": false,
      "order": { "player": 1, "nav": 2, "logo": 3 },
      "zones": {
        "player": { "minPx": 0 },
        "nav":    { "minPx": 0 },
        "logo":   { "minPx": 0 }
      },
      "vars": {
        "--player-btn-size": "28px",
        "--player-icon-size": "18px",
        "--player-title-max-w": "160px",
        "--player-title-font": "12px",
        "--player-time-font": "11px",
        "--seek-max-w": "none",
        "--seek-min-w": "60px",
        "--nav-font": "12px",
        "--nav-padding": "6px 10px",
        "--logo-img-h": "14px",
        "--logo-padding": "3px 10px"
      }
    },
    {
      "name": "touch-tablet",
      "_comment": "Touch device, 768-1023px. iPad etc. Horizontal but no volume.",
      "device": "touch",
      "minWidth": 768,
      "maxWidth": 1023,
      "stacked": false,
      "height": 56,
      "volumeVisible": false,
      "zones": {
        "player": { "minPx": 200 },
        "nav":    { "minPx": 0, "maxPx": 400 },
        "logo":   { "minPx": 50, "maxPx": 120 }
      },
      "vars": {
        "--player-btn-size": "30px",
        "--player-icon-size": "20px",
        "--player-title-max-w": "180px",
        "--player-title-font": "12px",
        "--seek-max-w": "180px",
        "--nav-font": "13px",
        "--nav-padding": "8px 14px",
        "--logo-img-h": "22px",
        "--logo-padding": "4px 14px",
        "--user-icon-size": "16px",
        "--user-name-font": "10px",
        "--user-logout-font": "8px",
        "--user-cell-padding": "4px 10px"
      }
    },
    {
      "name": "touch-wide",
      "_comment": "Touch device, ≥1024px. iPad Pro landscape etc. Full layout, no volume.",
      "device": "touch",
      "minWidth": 1024,
      "stacked": false,
      "height": 65,
      "volumeVisible": false,
      "zones": {
        "player": { "minPx": 280 },
        "nav":    { "minPx": 0 },
        "logo":   { "minPx": 60 }
      },
      "vars": {
        "--player-btn-size": "40px",
        "--player-icon-size": "32px",
        "--player-title-max-w": "400px",
        "--player-title-font": "13px",
        "--seek-max-w": "200px",
        "--nav-font": "14px",
        "--nav-padding": "10px 20px",
        "--logo-img-h": "34px",
        "--logo-padding": "10px 30px 8px"
      }
    },
    {
      "name": "desktop-narrow",
      "_comment": "Desktop/pointer device dragged narrow. NOT a phone. Horizontal, all controls, volume visible.",
      "device": "pointer",
      "maxWidth": 1023,
      "stacked": false,
      "height": 50,
      "volumeVisible": true,
      "zones": {
        "player": { "minPx": 200 },
        "nav":    { "minPx": 0, "maxPx": 350 },
        "logo":   { "minPx": 40, "maxPx": 100 }
      },
      "vars": {
        "--player-btn-size": "26px",
        "--player-icon-size": "18px",
        "--player-title-max-w": "140px",
        "--player-title-font": "12px",
        "--seek-max-w": "140px",
        "--vol-track-w": "50px",
        "--nav-font": "12px",
        "--nav-padding": "6px 10px",
        "--logo-img-h": "18px",
        "--logo-padding": "4px 12px",
        "--user-icon-size": "14px",
        "--user-name-font": "9px",
        "--user-logout-font": "7px",
        "--user-cell-padding": "3px 8px"
      }
    },
    {
      "name": "standard",
      "_comment": "Desktop/pointer, 1024-1599px. Normal laptop/monitor.",
      "device": "pointer",
      "minWidth": 1024,
      "maxWidth": 1599,
      "stacked": false,
      "height": 75,
      "volumeVisible": true,
      "zones": {
        "player": { "minPx": 280 },
        "nav":    { "minPx": 0 },
        "logo":   { "minPx": 60 }
      },
      "vars": {
        "--player-btn-size": "45px",
        "--player-icon-size": "40px",
        "--player-title-max-w": "500px",
        "--player-title-font": "13px",
        "--seek-max-w": "200px",
        "--vol-track-w": "100px",
        "--nav-font": "14px",
        "--nav-padding": "10px 20px",
        "--logo-img-h": "38px",
        "--logo-padding": "12px 34px 10px",
        "--user-icon-size": "20px",
        "--user-name-font": "11px",
        "--user-logout-font": "9px",
        "--user-cell-padding": "6px 16px"
      }
    },
    {
      "name": "wide",
      "_comment": "Desktop/pointer, ≥1600px. Large monitors.",
      "device": "pointer",
      "minWidth": 1600,
      "stacked": false,
      "height": 75,
      "volumeVisible": true,
      "zones": {
        "player": { "minPx": 400 },
        "nav":    { "minPx": 0 },
        "logo":   { "minPx": 80 }
      },
      "vars": {
        "--player-btn-size": "45px",
        "--player-icon-size": "40px",
        "--player-title-max-w": "600px",
        "--player-title-font": "14px",
        "--seek-max-w": "300px",
        "--vol-track-w": "120px",
        "--nav-font": "14px",
        "--nav-padding": "10px 24px",
        "--logo-img-h": "38px",
        "--logo-padding": "12px 34px 10px"
      }
    }
  ],

  "zones": {
    "_comment": "Default zone constraints. Profiles override these.",
    "player": { "priority": 1, "greedy": true, "minPx": 200 },
    "nav":    { "priority": 2, "shrink": 0, "minPx": 0 },
    "logo":   { "priority": 3, "shrink": 0, "widthPx": 80, "minPx": 60 }
  },

  "nav": {
    "items": ["playlists", "film", "contact", "login", "cart"],
    "separator": "1px solid rgba(43, 127, 140, 0.25)"
  },

  "logo": {
    "tagColor": "#829D9E",
    "tagText": "rdxenv 24/25/26"
  },

  "toggle": {
    "text": "PLAYER I/O",
    "textTransform": "uppercase",
    "letterSpacing": "1.5px"
  },

  "mobile": {
    "_comment": "Legacy compat. Profiles replace this.",
    "stackBreakpoint": 767,
    "layout": "stacked"
  }
}